Metadata-Version: 2.1
Name: fpsm
Version: 0.0.1.3
Summary: Functional programming support modules
Home-page: https://github.com/KeisukeToyota/fpsm
Author: KeisukeToyota
Author-email: hm.pudding0715@gmail.com
Maintainer: KeisukeToyota
Maintainer-email: hm.pudding0715@gmail.com
License: MIT
Platform: UNKNOWN
